kaito_model/__init__.py
kaito_model/__main__.py
kaito_model/discord/discord_base.py
kaito_model/discord/message.py
kaito_model/discord/role.py
kaito_model/example.py
kaito_model/mapper/casedict.py
kaito_model/mapper/object_mapper.py
kaito_model/mapper/object_mapper_exception.py
kaito_model/pynamo/discord/discord_message.py
kaito_model/pynamo/discord/discord_role.py
kaito_model/pynamo/pynamo_base_model.py
kaito_model-0.1.4.dist-info/WHEEL
kaito_model-0.1.4.dist-info/METADATA
kaito_model-0.1.4.dist-info/RECORD
